MCMC_AU/Decryption.py
MCMC_AU/McmcException.py
MCMC_AU/McmcFile.py
MCMC_AU/Sampling.py
MCMC_AU/__init__.py
mcmc_au-1.0.0.dist-info/METADATA
mcmc_au-1.0.0.dist-info/WHEEL
mcmc_au-1.0.0.dist-info/licenses/LICENSE
mcmc_au-1.0.0.dist-info/RECORD
