Metadata-Version: 2.1
Name: MCMC_AU
Version: 1.0.0
Project-URL: Homepage, https://github.com/elamani-drawing/mcmc-au
Author-email: "Au = OR [79]" <faux@example.com>, glogwa68 <faux@example.com>
License: MIT License
Classifier: License :: OSI Approved :: MIT License
Classifier: Operating System :: OS Independent
Classifier: Programming Language :: Python :: 3
Requires-Python: >=3.7
